{
  "metadata": {
    "name": "Boyles, Aubrey",
    "address": "37 Loomis Street\nMontpelier, VT 05602\nCity: Montpelier",
    "slug": "boyles-aubrey"
  },
  "availability": {
    "2025-07-22": {
      "infant": 1,
      "toddler": 1
    },
    "2025-07-23": {
      "infant": 1,
      "toddler": 1
    },
    "2025-07-24": {
      "infant": 1,
      "toddler": 1
    },
    "2025-07-25": {
      "infant": 1,
      "toddler": 1
    },
    "2025-07-26": {
      "infant": 1,
      "toddler": 1
    },
    "2025-07-29": {
      "infant": 1,
      "toddler": 1
    },
    "2025-07-30": {
      "infant": 1,
      "toddler": 1
    }
  }
}